cdk8s_metaflow/__init__.py
cdk8s_metaflow/py.typed
cdk8s_metaflow/_jsii/__init__.py
cdk8s_metaflow/_jsii/cdk8s-metaflow@0.0.10.jsii.tgz
cdk8s_metaflow-0.0.10.dist-info/LICENSE
cdk8s_metaflow-0.0.10.dist-info/METADATA
cdk8s_metaflow-0.0.10.dist-info/WHEEL
cdk8s_metaflow-0.0.10.dist-info/top_level.txt
cdk8s_metaflow-0.0.10.dist-info/RECORD
