Metadata-Version: 2.1
Name: cdk8s-metaflow
Version: 0.0.10
Summary: cdk8s-metaflow
Home-page: https://github.com/bcgalvin/cdk8s-metaflow.git
Author: Bryan Galvin<bcgalvin@gmail.com>
License: Apache-2.0
Project-URL: Source, https://github.com/bcgalvin/cdk8s-metaflow.git
Classifier: Intended Audience :: Developers
Classifier: Operating System :: OS Independent
Classifier: Programming Language :: JavaScript
Classifier: Programming Language :: Python :: 3 :: Only
Classifier: Programming Language :: Python :: 3.7
Classifier: Programming Language :: Python :: 3.8
Classifier: Programming Language :: Python :: 3.9
Classifier: Programming Language :: Python :: 3.10
Classifier: Typing :: Typed
Classifier: Development Status :: 4 - Beta
Classifier: License :: OSI Approved
Requires-Python: ~=3.7
License-File: LICENSE
Requires-Dist: cdk8s-plus-21 (==2.0.0.b12)
Requires-Dist: cdk8s (<3.0.0,>=2.4.7)
Requires-Dist: constructs (<11.0.0,>=10.1.83)
Requires-Dist: jsii (<2.0.0,>=1.65.0)
Requires-Dist: publication (>=0.0.3)
Requires-Dist: typeguard (~=2.13.3)
